{
  "dashboard": {
    "__requires": [
      {
        "type": "grafana",
        "id": "grafana",
        "name": "Grafana",
        "version": "9.0.2"
      },
      {
        "type": "datasource",
        "id": "prometheus",
        "name": "Prometheus",
        "version": "1.0.0"
      },
      {
        "type": "panel",
        "id": "stat",
        "name": "Stat",
        "version": ""
      },
      {
        "type": "panel",
        "id": "table",
        "name": "Table",
        "version": ""
      },
      {
        "type": "panel",
        "id": "text",
        "name": "Text",
        "version": ""
      },
      {
        "type": "panel",
        "id": "timeseries",
        "name": "Time series",
        "version": ""
      }
    ],
    "description": "Displays metrics collected by methods annotated with MicroProfile Fault Tolerance annotations",
    "editable": true,
    "panels": [
      {
        "collapsed": false,
        "datasource": {
          "type": "prometheus",
          "uid": "Prometheus"
        },
        "gridPos": {
          "h": 1,
          "w": 24,
          "x": 0,
          "y": 0
        },
        "id": 72,
        "panels": [],
        "targets": [
          {
            "datasource": {
              "type": "prometheus",
              "uid": "Prometheus"
            },
            "refId": "A"
          }
        ],
        "title": "Instructions",
        "type": "row"
      },
      {
        "datasource": {
          "type": "prometheus",
          "uid": "Prometheus"
        },
        "description": "",
        "gridPos": {
          "h": 5,
          "w": 24,
          "x": 0,
          "y": 1
        },
        "id": 70,
        "options": {
          "content": "This dashboard displays metrics collected by methods that are annotated with [MicroProfile Fault Tolerance](https://github.com/eclipse/microprofile-fault-tolerance/) annotations.\n\nIf no methods are annotated with a given Fault Tolerance Strategy, e.g. `@Retry`, then the respective panels will display \"No data\". This differs from no methods __applying__ the strategy, which would display 0 (or similar).",
          "mode": "markdown"
        },
        "pluginVersion": "9.0.2",
        "targets": [
          {
            "datasource": {
              "type": "prometheus",
              "uid": "Prometheus"
            },
            "refId": "A"
          }
        ],
        "title": "Instructions",
        "type": "text"
      },
      {
        "collapsed": false,
        "datasource": {
          "type": "prometheus",
          "uid": "Prometheus"
        },
        "gridPos": {
          "h": 1,
          "w": 24,
          "x": 0,
          "y": 6
        },
        "id": 32,
        "panels": [],
        "targets": [
          {
            "datasource": {
              "type": "prometheus",
              "uid": "Prometheus"
            },
            "refId": "A"
          }
        ],
        "title": "Basic Metrics",
        "type": "row"
      },
      {
        "datasource": {
          "type": "prometheus",
          "uid": "Prometheus"
        },
        "description": "The percentage of method invocations (for methods annotated with `@Fallback`) which resulted in fallback being applied over the past $avg_period.\n\nIf no methods are annotated with `@Fallback`, \"No data\" will be displayed.",
        "fieldConfig": {
          "defaults": {
            "mappings": [],
            "max": 100,
            "min": 0,
            "thresholds": {
              "mode": "absolute",
              "steps": [
                {
                  "color": "rgb(125, 125, 125)",
                  "value": null
                },
                {
                  "color": "green",
                  "value": 0
                },
                {
                  "color": "orange",
                  "value": 5
                },
                {
                  "color": "red",
                  "value": 10
                }
              ]
            },
            "unit": "percent"
          },
          "overrides": []
        },
        "gridPos": {
          "h": 5,
          "w": 4,
          "x": 2,
          "y": 7
        },
        "id": 64,
        "options": {
          "colorMode": "value",
          "graphMode": "none",
          "justifyMode": "auto",
          "orientation": "auto",
          "reduceOptions": {
            "calcs": [
              "last"
            ],
            "fields": "",
            "values": false
          },
          "textMode": "auto"
        },
        "pluginVersion": "9.0.2",
        "targets": [
          {
            "datasource": {
              "type": "prometheus",
              "uid": "Prometheus"
            },
            "expr": "sum without (result, fallback)(increase(base_ft_invocations_total{instance=~`${instance}`, fallback='applied'}[$avg_period]))*100/\nsum without (result, fallback)(increase(base_ft_invocations_total{instance=~`${instance}`}[$avg_period]))",
            "interval": "",
            "legendFormat": "",
            "refId": "A"
          }
        ],
        "title": "Fallbacks [$avg_period]",
        "type": "stat"
      },
      {
        "datasource": {
          "type": "prometheus",
          "uid": "Prometheus"
        },
        "description": "The percentage of method invocations (for methods annotated with `@Retry`) which resulted in a retry over the past $avg_period.\n\nIf no methods are annotated with `@Retry`, \"No data\" will be displayed.",
        "fieldConfig": {
          "defaults": {
            "mappings": [],
            "max": 100,
            "min": 0,
            "thresholds": {
              "mode": "absolute",
              "steps": [
                {
                  "color": "rgb(125, 125, 125)",
                  "value": null
                },
                {
                  "color": "green",
                  "value": 0
                },
                {
                  "color": "orange",
                  "value": 5
                },
                {
                  "color": "red",
                  "value": 10
                }
              ]
            },
            "unit": "percent"
          },
          "overrides": []
        },
        "gridPos": {
          "h": 5,
          "w": 4,
          "x": 6,
          "y": 7
        },
        "id": 65,
        "options": {
          "colorMode": "value",
          "graphMode": "none",
          "justifyMode": "auto",
          "orientation": "auto",
          "reduceOptions": {
            "calcs": [
              "last"
            ],
            "fields": "",
            "values": false
          },
          "textMode": "auto"
        },
        "pluginVersion": "9.0.2",
        "targets": [
          {
            "datasource": {
              "type": "prometheus",
              "uid": "Prometheus"
            },
            "expr": "sum without (retryResult, retried)(increase(base_ft_retry_calls_total{instance=~`${instance}`, retried='true'}[$avg_period]))*100/\nsum without (retryResult, retried)(increase(base_ft_retry_calls_total{instance=~`${instance}`}[$avg_period]))",
            "interval": "",
            "legendFormat": "",
            "refId": "A"
          }
        ],
        "title": "Retries [$avg_period]",
        "type": "stat"
      },
      {
        "datasource": {
          "type": "prometheus",
          "uid": "Prometheus"
        },
        "description": "The percentage of method invocations (for methods annotated with `@Timeout`) which resulted in a timeout over the past $avg_period.\n\nIf no methods are annotated with `@Timeout`, \"No data\" will be displayed.",
        "fieldConfig": {
          "defaults": {
            "mappings": [],
            "max": 100,
            "min": 0,
            "thresholds": {
              "mode": "absolute",
              "steps": [
                {
                  "color": "rgb(125, 125, 125)",
                  "value": null
                },
                {
                  "color": "green",
                  "value": 0
                },
                {
                  "color": "orange",
                  "value": 5
                },
                {
                  "color": "red",
                  "value": 10
                }
              ]
            },
            "unit": "percent"
          },
          "overrides": []
        },
        "gridPos": {
          "h": 5,
          "w": 4,
          "x": 10,
          "y": 7
        },
        "id": 66,
        "options": {
          "colorMode": "value",
          "graphMode": "none",
          "justifyMode": "auto",
          "orientation": "auto",
          "reduceOptions": {
            "calcs": [
              "last"
            ],
            "fields": "",
            "values": false
          },
          "textMode": "auto"
        },
        "pluginVersion": "9.0.2",
        "targets": [
          {
            "datasource": {
              "type": "prometheus",
              "uid": "Prometheus"
            },
            "expr": "sum without (timedOut)(increase(base_ft_timeout_calls_total{instance=~`${instance}`, timedOut='true'}[$avg_period]))*100/\nsum without (timedOut)(increase(base_ft_timeout_calls_total{instance=~`${instance}`}[$avg_period]))",
            "interval": "",
            "legendFormat": "",
            "refId": "A"
          }
        ],
        "title": "Timeouts [$avg_period]",
        "type": "stat"
      },
      {
        "datasource": {
          "type": "prometheus",
          "uid": "Prometheus"
        },
        "description": "The percentage of method invocations (for methods annotated with `@Bulkhead`) which were rejected by the bulkhead over the last $avg_period.\n\nIf no methods are annotated with `@Bulkhead`, \"No data\" will be displayed.",
        "fieldConfig": {
          "defaults": {
            "color": {
              "mode": "thresholds"
            },
            "mappings": [],
            "max": 100,
            "min": 0,
            "thresholds": {
              "mode": "absolute",
              "steps": [
                {
                  "color": "rgb(125, 125, 125)",
                  "value": null
                },
                {
                  "color": "green",
                  "value": 0
                },
                {
                  "color": "orange",
                  "value": 5
                },
                {
                  "color": "red",
                  "value": 10
                }
              ]
            },
            "unit": "percent"
          },
          "overrides": []
        },
        "gridPos": {
          "h": 5,
          "w": 4,
          "x": 14,
          "y": 7
        },
        "id": 67,
        "options": {
          "colorMode": "value",
          "graphMode": "none",
          "justifyMode": "auto",
          "orientation": "auto",
          "reduceOptions": {
            "calcs": [
              "last"
            ],
            "fields": "",
            "values": false
          },
          "textMode": "auto"
        },
        "pluginVersion": "9.0.2",
        "targets": [
          {
            "datasource": {
              "type": "prometheus",
              "uid": "Prometheus"
            },
            "expr": "sum without (bulkheadResult)(increase(base_ft_bulkhead_calls_total{instance=~`${instance}`, bulkheadResult='rejected'}[$avg_period]))*100/\nsum without (bulkheadResult)(increase(base_ft_bulkhead_calls_total{instance=~`${instance}`}[$avg_period]))",
            "instant": false,
            "interval": "",
            "legendFormat": "",
            "refId": "A"
          }
        ],
        "title": "Bulkhead Rejections [$avg_period]",
        "type": "stat"
      },
      {
        "datasource": {
          "type": "prometheus",
          "uid": "Prometheus"
        },
        "description": "The percentage of method invocations (for methods annotated with `@CircuitBreaker`) which were rejected by an open circuit breaker over the last $avg_period.\n\nIf no methods are annotated with `@CircuitBreaker`, \"No data\" will be displayed.",
        "fieldConfig": {
          "defaults": {
            "color": {
              "mode": "thresholds"
            },
            "mappings": [],
            "max": 100,
            "min": 0,
            "thresholds": {
              "mode": "absolute",
              "steps": [
                {
                  "color": "rgb(128, 128, 128)",
                  "value": null
                },
                {
                  "color": "green",
                  "value": 0
                },
                {
                  "color": "orange",
                  "value": 5
                },
                {
                  "color": "red",
                  "value": 10
                }
              ]
            },
            "unit": "percent"
          },
          "overrides": []
        },
        "gridPos": {
          "h": 5,
          "w": 4,
          "x": 18,
          "y": 7
        },
        "id": 68,
        "options": {
          "colorMode": "value",
          "graphMode": "none",
          "justifyMode": "auto",
          "orientation": "auto",
          "reduceOptions": {
            "calcs": [
              "last"
            ],
            "fields": "",
            "values": false
          },
          "textMode": "auto"
        },
        "pluginVersion": "9.0.2",
        "targets": [
          {
            "datasource": {
              "type": "prometheus",
              "uid": "Prometheus"
            },
            "expr": "sum without (circuitBreakerResult)(increase(base_ft_circuitbreaker_calls_total{instance=~`${instance}`, circuitBreakerResult='circuitBreakerOpen'}[$avg_period])*100)\n/\nsum without (circuitBreakerResult)(increase(base_ft_circuitbreaker_calls_total{instance=~`${instance}`}[$avg_period]))",
            "instant": false,
            "interval": "",
            "legendFormat": "",
            "refId": "A"
          }
        ],
        "title": "Circuit Breaker Rejections [$avg_period]",
        "type": "stat"
      },
      {
        "datasource": {
          "type": "prometheus",
          "uid": "Prometheus"
        },
        "description": "Percentage of calls which resulted in a failure.\n\nThis graph is showing failures after all fault tolerance processing has taken place, including fallback.\n\nIf no methods annotated with fault tolerance annotations are failing after the strategies have been applied, \"No data\" will be displayed.",
        "fieldConfig": {
          "defaults": {
            "custom": {
              "align": "auto",
              "displayMode": "auto",
              "filterable": false,
              "inspect": false
            },
            "decimals": 2,
            "mappings": [],
            "thresholds": {
              "mode": "absolute",
              "steps": [
                {
                  "color": "green",
                  "value": null
                }
              ]
            },
            "unit": "percent"
          },
          "overrides": [
            {
              "matcher": {
                "id": "byName",
                "options": "Value"
              },
              "properties": [
                {
                  "id": "displayName",
                  "value": "Failure rate %"
                },
                {
                  "id": "custom.displayMode",
                  "value": "gradient-gauge"
                },
                {
                  "id": "thresholds",
                  "value": {
                    "mode": "absolute",
                    "steps": [
                      {
                        "color": "red",
                        "value": null
                      }
                    ]
                  }
                }
              ]
            }
          ]
        },
        "gridPos": {
          "h": 5,
          "w": 24,
          "x": 0,
          "y": 12
        },
        "id": 62,
        "links": [],
        "options": {
          "footer": {
            "fields": "",
            "reducer": [
              "sum"
            ],
            "show": false
          },
          "showHeader": true,
          "sortBy": [
            {
              "desc": true,
              "displayName": "Failure rate %"
            }
          ]
        },
        "pluginVersion": "9.0.2",
        "targets": [
          {
            "datasource": {
              "type": "prometheus",
              "uid": "Prometheus"
            },
            "expr": "topk(${topK}, \nsum without (result, fallback)(rate(base_ft_invocations_total{instance=~`${instance}`, result='exceptionThrown'}[$avg_period])) * 100 \n/ \nsum without (result, fallback)(rate(base_ft_invocations_total{instance=~`${instance}`}[$avg_period])) \n) \n> 0 ",
            "format": "table",
            "hide": false,
            "instant": true,
            "interval": "",
            "legendFormat": "",
            "refId": "A"
          }
        ],
        "title": "Top $topK most frequently failing methods over the last $avg_period",
        "transformations": [
          {
            "id": "organize",
            "options": {
              "excludeByName": {
                "Time": true,
                "job": true
              },
              "indexByName": {},
              "renameByName": {
                "Time": ""
              }
            }
          }
        ],
        "type": "table"
      },
      {
        "datasource": {
          "type": "prometheus",
          "uid": "Prometheus"
        },
        "description": "Number of method invocations which occurred per second for methods with fault tolerance annotations.",
        "fieldConfig": {
          "defaults": {
            "color": {
              "mode": "palette-classic"
            },
            "custom": {
              "axisLabel": "Invocations per second",
              "axisPlacement": "auto",
              "barAlignment": 0,
              "drawStyle": "line",
              "fillOpacity": 10,
              "gradientMode": "none",
              "hideFrom": {
                "legend": false,
                "tooltip": false,
                "viz": false
              },
              "lineInterpolation": "linear",
              "lineStyle": {
                "fill": "solid"
              },
              "lineWidth": 1,
              "pointSize": 5,
              "scaleDistribution": {
                "type": "linear"
              },
              "showPoints": "never",
              "spanNulls": false,
              "stacking": {
                "group": "A",
                "mode": "none"
              },
              "thresholdsStyle": {
                "mode": "off"
              }
            },
            "links": [],
            "mappings": [],
            "min": 0,
            "thresholds": {
              "mode": "absolute",
              "steps": [
                {
                  "color": "green",
                  "value": null
                },
                {
                  "color": "red",
                  "value": 80
                }
              ]
            },
            "unit": "short"
          },
          "overrides": []
        },
        "gridPos": {
          "h": 9,
          "w": 12,
          "x": 0,
          "y": 17
        },
        "id": 22,
        "links": [],
        "options": {
          "legend": {
            "calcs": [
              "mean",
              "max",
              "min"
            ],
            "displayMode": "table",
            "placement": "bottom"
          },
          "tooltip": {
            "mode": "multi",
            "sort": "none"
          }
        },
        "pluginVersion": "9.0.2",
        "repeat": "method",
        "repeatDirection": "v",
        "targets": [
          {
            "datasource": {
              "type": "prometheus",
              "uid": "Prometheus"
            },
            "expr": "sum without (result, fallback)(rate(base_ft_invocations_total{instance=~`${instance}`}[$avg_period]))",
            "format": "time_series",
            "hide": false,
            "interval": "",
            "intervalFactor": 1,
            "legendFormat": "instance: {{instance}}, method: {{method}}",
            "refId": "A"
          }
        ],
        "title": "Method invocations [per second, avg $avg_period]",
        "type": "timeseries"
      },
      {
        "datasource": {
          "type": "prometheus",
          "uid": "Prometheus"
        },
        "description": "Percentage of calls which resulted in a failure.\n\nThis graph is showing failures after all fault tolerance processing has taken place, including fallback.",
        "fieldConfig": {
          "defaults": {
            "color": {
              "mode": "palette-classic"
            },
            "custom": {
              "axisLabel": "",
              "axisPlacement": "auto",
              "barAlignment": 0,
              "drawStyle": "line",
              "fillOpacity": 10,
              "gradientMode": "none",
              "hideFrom": {
                "legend": false,
                "tooltip": false,
                "viz": false
              },
              "lineInterpolation": "linear",
              "lineWidth": 1,
              "pointSize": 5,
              "scaleDistribution": {
                "type": "linear"
              },
              "showPoints": "never",
              "spanNulls": false,
              "stacking": {
                "group": "A",
                "mode": "none"
              },
              "thresholdsStyle": {
                "mode": "off"
              }
            },
            "links": [],
            "mappings": [],
            "max": 101,
            "min": 0,
            "thresholds": {
              "mode": "absolute",
              "steps": [
                {
                  "color": "green",
                  "value": null
                },
                {
                  "color": "red",
                  "value": 80
                }
              ]
            },
            "unit": "percent"
          },
          "overrides": []
        },
        "gridPos": {
          "h": 9,
          "w": 12,
          "x": 12,
          "y": 17
        },
        "id": 4,
        "links": [],
        "options": {
          "legend": {
            "calcs": [
              "mean",
              "max",
              "min"
            ],
            "displayMode": "table",
            "placement": "bottom"
          },
          "tooltip": {
            "mode": "multi",
            "sort": "none"
          }
        },
        "pluginVersion": "9.0.2",
        "targets": [
          {
            "datasource": {
              "type": "prometheus",
              "uid": "Prometheus"
            },
            "expr": "sum without (result, fallback)(rate(base_ft_invocations_total{instance=~`${instance}`, result='exceptionThrown'}[$avg_period])) * 100 \n/ \nsum without (result, fallback)(rate(base_ft_invocations_total{instance=~`${instance}`}[$avg_period]))",
            "format": "time_series",
            "interval": "",
            "intervalFactor": 1,
            "legendFormat": "instance: {{instance}}, method: {{method}}",
            "refId": "A"
          }
        ],
        "title": "Failure rate [%, avg $avg_period]",
        "type": "timeseries"
      },
      {
        "collapsed": false,
        "datasource": {
          "type": "prometheus",
          "uid": "Prometheus"
        },
        "gridPos": {
          "h": 1,
          "w": 24,
          "x": 0,
          "y": 26
        },
        "id": 38,
        "panels": [],
        "targets": [
          {
            "datasource": {
              "type": "prometheus",
              "uid": "Prometheus"
            },
            "refId": "A"
          }
        ],
        "title": "Fallback Metrics",
        "type": "row"
      },
      {
        "datasource": {
          "type": "prometheus",
          "uid": "Prometheus"
        },
        "description": "Percentage of method invocations which resulted in fallback being applied over the past $avg_period.",
        "fieldConfig": {
          "defaults": {
            "color": {
              "mode": "palette-classic"
            },
            "custom": {
              "axisLabel": "",
              "axisPlacement": "auto",
              "barAlignment": 0,
              "drawStyle": "line",
              "fillOpacity": 10,
              "gradientMode": "none",
              "hideFrom": {
                "legend": false,
                "tooltip": false,
                "viz": false
              },
              "lineInterpolation": "linear",
              "lineWidth": 1,
              "pointSize": 5,
              "scaleDistribution": {
                "type": "linear"
              },
              "showPoints": "never",
              "spanNulls": false,
              "stacking": {
                "group": "A",
                "mode": "none"
              },
              "thresholdsStyle": {
                "mode": "off"
              }
            },
            "links": [],
            "mappings": [],
            "max": 101,
            "min": 0,
            "thresholds": {
              "mode": "absolute",
              "steps": [
                {
                  "color": "green",
                  "value": null
                },
                {
                  "color": "red",
                  "value": 80
                }
              ]
            },
            "unit": "percent"
          },
          "overrides": []
        },
        "gridPos": {
          "h": 9,
          "w": 12,
          "x": 0,
          "y": 27
        },
        "id": 10,
        "links": [],
        "options": {
          "legend": {
            "calcs": [
              "mean",
              "max",
              "min"
            ],
            "displayMode": "table",
            "placement": "bottom"
          },
          "tooltip": {
            "mode": "multi",
            "sort": "none"
          }
        },
        "pluginVersion": "9.0.2",
        "targets": [
          {
            "datasource": {
              "type": "prometheus",
              "uid": "Prometheus"
            },
            "expr": "sum without (result, fallback)(rate(base_ft_invocations_total{instance=~`${instance}`, fallback='applied'}[$avg_period])) * 100 \n/ \nsum without (result, fallback)(rate(base_ft_invocations_total{instance=~`${instance}`}[$avg_period]))",
            "format": "time_series",
            "interval": "",
            "intervalFactor": 1,
            "legendFormat": "instance: {{instance}}, method: {{method}}",
            "refId": "A"
          }
        ],
        "title": "Invocations triggering fallback [%, avg $avg_period]",
        "type": "timeseries"
      },
      {
        "datasource": {
          "type": "prometheus",
          "uid": "Prometheus"
        },
        "description": "Percentage of method invocations which failed once fallback had been applied.",
        "fieldConfig": {
          "defaults": {
            "color": {
              "mode": "palette-classic"
            },
            "custom": {
              "axisLabel": "",
              "axisPlacement": "auto",
              "barAlignment": 0,
              "drawStyle": "line",
              "fillOpacity": 10,
              "gradientMode": "none",
              "hideFrom": {
                "legend": false,
                "tooltip": false,
                "viz": false
              },
              "lineInterpolation": "linear",
              "lineWidth": 1,
              "pointSize": 5,
              "scaleDistribution": {
                "type": "linear"
              },
              "showPoints": "never",
              "spanNulls": false,
              "stacking": {
                "group": "A",
                "mode": "none"
              },
              "thresholdsStyle": {
                "mode": "off"
              }
            },
            "links": [],
            "mappings": [],
            "max": 101,
            "min": 0,
            "thresholds": {
              "mode": "absolute",
              "steps": [
                {
                  "color": "green",
                  "value": null
                },
                {
                  "color": "red",
                  "value": 80
                }
              ]
            },
            "unit": "percent"
          },
          "overrides": []
        },
        "gridPos": {
          "h": 9,
          "w": 12,
          "x": 12,
          "y": 27
        },
        "id": 42,
        "options": {
          "legend": {
            "calcs": [
              "mean",
              "max",
              "min"
            ],
            "displayMode": "table",
            "placement": "bottom"
          },
          "tooltip": {
            "mode": "multi",
            "sort": "none"
          }
        },
        "pluginVersion": "9.0.2",
        "targets": [
          {
            "datasource": {
              "type": "prometheus",
              "uid": "Prometheus"
            },
            "expr": "sum without (result, fallback)(rate(base_ft_invocations_total{instance=~`${instance}`, fallback='applied',result='exceptionThrown'}[$avg_period])) * 100 \n/ \nsum without (result, fallback)(rate(base_ft_invocations_total{instance=~`${instance}`, fallback='applied'}[$avg_period]))",
            "interval": "",
            "legendFormat": "instance: {{instance}}, method: {{method}}",
            "refId": "A"
          }
        ],
        "title": "Invocations failed after fallback [%, avg $avg_period]",
        "type": "timeseries"
      },
      {
        "collapsed": false,
        "datasource": {
          "type": "prometheus",
          "uid": "Prometheus"
        },
        "gridPos": {
          "h": 1,
          "w": 24,
          "x": 0,
          "y": 36
        },
        "id": 24,
        "panels": [],
        "targets": [
          {
            "datasource": {
              "type": "prometheus",
              "uid": "Prometheus"
            },
            "refId": "A"
          }
        ],
        "title": "Retry Metrics",
        "type": "row"
      },
      {
        "datasource": {
          "type": "prometheus",
          "uid": "Prometheus"
        },
        "description": "Percentage of method invocation which failed, despite retrying, over the last $avg_period.",
        "fieldConfig": {
          "defaults": {
            "color": {
              "mode": "palette-classic"
            },
            "custom": {
              "axisLabel": "",
              "axisPlacement": "auto",
              "barAlignment": 0,
              "drawStyle": "line",
              "fillOpacity": 10,
              "gradientMode": "none",
              "hideFrom": {
                "legend": false,
                "tooltip": false,
                "viz": false
              },
              "lineInterpolation": "linear",
              "lineWidth": 1,
              "pointSize": 5,
              "scaleDistribution": {
                "type": "linear"
              },
              "showPoints": "never",
              "spanNulls": false,
              "stacking": {
                "group": "A",
                "mode": "none"
              },
              "thresholdsStyle": {
                "mode": "off"
              }
            },
            "links": [],
            "mappings": [],
            "max": 101,
            "min": 0,
            "thresholds": {
              "mode": "absolute",
              "steps": [
                {
                  "color": "green",
                  "value": null
                },
                {
                  "color": "red",
                  "value": 80
                }
              ]
            },
            "unit": "percent"
          },
          "overrides": []
        },
        "gridPos": {
          "h": 9,
          "w": 12,
          "x": 0,
          "y": 37
        },
        "id": 9,
        "links": [],
        "options": {
          "legend": {
            "calcs": [
              "mean",
              "max",
              "min"
            ],
            "displayMode": "table",
            "placement": "bottom"
          },
          "tooltip": {
            "mode": "multi",
            "sort": "none"
          }
        },
        "pluginVersion": "9.0.2",
        "targets": [
          {
            "datasource": {
              "type": "prometheus",
              "uid": "Prometheus"
            },
            "expr": "sum without (retryResult, retried)(rate(base_ft_retry_calls_total{instance=~`${instance}`, retried='true', retryResult!='valueReturned'}[$avg_period])*100)\n/\nsum without (retryResult, retried)(rate(base_ft_retry_calls_total{instance=~`${instance}`}[$avg_period]))",
            "format": "time_series",
            "interval": "",
            "intervalFactor": 1,
            "legendFormat": "instance: {{instance}}, method: {{method}}",
            "refId": "A"
          }
        ],
        "title": "Invocations failed despite retries [%, avg $avg_period]",
        "type": "timeseries"
      },
      {
        "datasource": {
          "type": "prometheus",
          "uid": "Prometheus"
        },
        "description": "Average number of retries which occurred for each method invocation.",
        "fieldConfig": {
          "defaults": {
            "color": {
              "mode": "palette-classic"
            },
            "custom": {
              "axisLabel": "Retries per invocation",
              "axisPlacement": "auto",
              "barAlignment": 0,
              "drawStyle": "line",
              "fillOpacity": 10,
              "gradientMode": "none",
              "hideFrom": {
                "legend": false,
                "tooltip": false,
                "viz": false
              },
              "lineInterpolation": "linear",
              "lineWidth": 1,
              "pointSize": 5,
              "scaleDistribution": {
                "type": "linear"
              },
              "showPoints": "never",
              "spanNulls": false,
              "stacking": {
                "group": "A",
                "mode": "none"
              },
              "thresholdsStyle": {
                "mode": "off"
              }
            },
            "links": [],
            "mappings": [],
            "min": 0,
            "thresholds": {
              "mode": "absolute",
              "steps": [
                {
                  "color": "green",
                  "value": null
                },
                {
                  "color": "red",
                  "value": 80
                }
              ]
            },
            "unit": "short"
          },
          "overrides": []
        },
        "gridPos": {
          "h": 9,
          "w": 12,
          "x": 12,
          "y": 37
        },
        "id": 8,
        "links": [],
        "options": {
          "legend": {
            "calcs": [
              "mean",
              "max",
              "min"
            ],
            "displayMode": "table",
            "placement": "bottom"
          },
          "tooltip": {
            "mode": "multi",
            "sort": "none"
          }
        },
        "pluginVersion": "9.0.2",
        "targets": [
          {
            "datasource": {
              "type": "prometheus",
              "uid": "Prometheus"
            },
            "expr": "sum without()(rate(base_ft_retry_retries_total{instance=~`${instance}`}[$avg_period]))\n/\nsum without (retried, retryResult)(rate(base_ft_retry_calls_total{instance=~`${instance}`}[$avg_period]))",
            "format": "time_series",
            "interval": "",
            "intervalFactor": 1,
            "legendFormat": "instance: {{instance}}, method: {{method}}",
            "refId": "A"
          }
        ],
        "title": "Retries per invocation [avg $avg_period]",
        "type": "timeseries"
      },
      {
        "collapsed": false,
        "datasource": {
          "type": "prometheus",
          "uid": "Prometheus"
        },
        "gridPos": {
          "h": 1,
          "w": 24,
          "x": 0,
          "y": 46
        },
        "id": 30,
        "panels": [],
        "targets": [
          {
            "datasource": {
              "type": "prometheus",
              "uid": "Prometheus"
            },
            "refId": "A"
          }
        ],
        "title": "Timeout Metrics",
        "type": "row"
      },
      {
        "datasource": {
          "type": "prometheus",
          "uid": "Prometheus"
        },
        "description": "Percentage of invocations which timed out",
        "fieldConfig": {
          "defaults": {
            "color": {
              "mode": "palette-classic"
            },
            "custom": {
              "axisLabel": "",
              "axisPlacement": "auto",
              "barAlignment": 0,
              "drawStyle": "line",
              "fillOpacity": 10,
              "gradientMode": "none",
              "hideFrom": {
                "legend": false,
                "tooltip": false,
                "viz": false
              },
              "lineInterpolation": "linear",
              "lineWidth": 1,
              "pointSize": 5,
              "scaleDistribution": {
                "type": "linear"
              },
              "showPoints": "never",
              "spanNulls": false,
              "stacking": {
                "group": "A",
                "mode": "none"
              },
              "thresholdsStyle": {
                "mode": "off"
              }
            },
            "links": [],
            "mappings": [],
            "max": 101,
            "min": 0,
            "thresholds": {
              "mode": "absolute",
              "steps": [
                {
                  "color": "green",
                  "value": null
                },
                {
                  "color": "red",
                  "value": 80
                }
              ]
            },
            "unit": "percent"
          },
          "overrides": []
        },
        "gridPos": {
          "h": 9,
          "w": 12,
          "x": 0,
          "y": 47
        },
        "id": 36,
        "links": [],
        "options": {
          "legend": {
            "calcs": [
              "mean",
              "max",
              "min"
            ],
            "displayMode": "table",
            "placement": "bottom"
          },
          "tooltip": {
            "mode": "multi",
            "sort": "none"
          }
        },
        "pluginVersion": "9.0.2",
        "targets": [
          {
            "datasource": {
              "type": "prometheus",
              "uid": "Prometheus"
            },
            "expr": "sum without (timedOut)(rate(base_ft_timeout_calls_total{instance=~`${instance}`, timedOut='true'}[$avg_period])) * 100\n/\nsum without (timedOut)(rate(base_ft_timeout_calls_total{instance=~`${instance}`}[$avg_period]))",
            "format": "time_series",
            "interval": "",
            "intervalFactor": 1,
            "legendFormat": "instance: {{instance}}, method: {{method}}",
            "refId": "A"
          }
        ],
        "title": "Invocations timed out [%, avg $avg_period]",
        "type": "timeseries"
      },
      {
        "datasource": {
          "type": "prometheus",
          "uid": "Prometheus"
        },
        "description": "The average duration a method with a timeout executes for to return a value, using a weighted average of the last 1000 executions.",
        "fieldConfig": {
          "defaults": {
            "color": {
              "mode": "palette-classic"
            },
            "custom": {
              "axisLabel": "",
              "axisPlacement": "auto",
              "barAlignment": 0,
              "drawStyle": "line",
              "fillOpacity": 10,
              "gradientMode": "none",
              "hideFrom": {
                "legend": false,
                "tooltip": false,
                "viz": false
              },
              "lineInterpolation": "linear",
              "lineWidth": 1,
              "pointSize": 5,
              "scaleDistribution": {
                "type": "linear"
              },
              "showPoints": "never",
              "spanNulls": false,
              "stacking": {
                "group": "A",
                "mode": "none"
              },
              "thresholdsStyle": {
                "mode": "off"
              }
            },
            "links": [],
            "mappings": [],
            "thresholds": {
              "mode": "absolute",
              "steps": [
                {
                  "color": "green",
                  "value": null
                },
                {
                  "color": "red",
                  "value": 80
                }
              ]
            },
            "unit": "s"
          },
          "overrides": []
        },
        "gridPos": {
          "h": 8,
          "w": 12,
          "x": 12,
          "y": 47
        },
        "id": 46,
        "options": {
          "legend": {
            "calcs": [
              "max",
              "min"
            ],
            "displayMode": "table",
            "placement": "bottom"
          },
          "tooltip": {
            "mode": "multi",
            "sort": "none"
          }
        },
        "pluginVersion": "9.0.2",
        "targets": [
          {
            "datasource": {
              "type": "prometheus",
              "uid": "Prometheus"
            },
            "expr": "base_ft_timeout_executionDuration_mean_seconds{instance=~`${instance}`}",
            "interval": "",
            "legendFormat": "instance: {{instance}}, method: {{method}}",
            "refId": "A"
          }
        ],
        "title": "Mean execution duration for methods with a timeout [s, avg 1000 exec.]",
        "type": "timeseries"
      },
      {
        "datasource": {
          "type": "prometheus",
          "uid": "Prometheus"
        },
        "description": "Shows the selected quantile of execution times using a weighted average of the last 1000 executions.\n\nThe quantiles should be understood like this: if the 0.99 quantile is 300ms, then 99% of executions took less than 300ms. (Conversely, 1% of executions took longer than 300ms.)",
        "fieldConfig": {
          "defaults": {
            "color": {
              "mode": "palette-classic"
            },
            "custom": {
              "axisLabel": "",
              "axisPlacement": "auto",
              "barAlignment": 0,
              "drawStyle": "line",
              "fillOpacity": 10,
              "gradientMode": "none",
              "hideFrom": {
                "legend": false,
                "tooltip": false,
                "viz": false
              },
              "lineInterpolation": "linear",
              "lineWidth": 1,
              "pointSize": 5,
              "scaleDistribution": {
                "type": "linear"
              },
              "showPoints": "never",
              "spanNulls": false,
              "stacking": {
                "group": "A",
                "mode": "none"
              },
              "thresholdsStyle": {
                "mode": "off"
              }
            },
            "links": [],
            "mappings": [],
            "thresholds": {
              "mode": "absolute",
              "steps": [
                {
                  "color": "green",
                  "value": null
                },
                {
                  "color": "red",
                  "value": 80
                }
              ]
            },
            "unit": "s"
          },
          "overrides": []
        },
        "gridPos": {
          "h": 9,
          "w": 12,
          "x": 0,
          "y": 56
        },
        "id": 34,
        "links": [],
        "options": {
          "legend": {
            "calcs": [
              "lastNotNull"
            ],
            "displayMode": "table",
            "placement": "bottom"
          },
          "tooltip": {
            "mode": "multi",
            "sort": "none"
          }
        },
        "pluginVersion": "9.0.2",
        "targets": [
          {
            "datasource": {
              "type": "prometheus",
              "uid": "Prometheus"
            },
            "expr": "base_ft_timeout_executionDuration_seconds{instance=~`${instance}`, quantile=`${quantile}`}",
            "format": "time_series",
            "interval": "",
            "intervalFactor": 1,
            "legendFormat": "instance: {{instance}}, method: {{method}}",
            "refId": "A"
          }
        ],
        "title": "$quantile quantile of execution duration for methods with a timeout [s, avg 1000 exec.]",
        "type": "timeseries"
      },
      {
        "collapsed": false,
        "datasource": {
          "type": "prometheus",
          "uid": "Prometheus"
        },
        "gridPos": {
          "h": 1,
          "w": 24,
          "x": 0,
          "y": 65
        },
        "id": 28,
        "panels": [],
        "targets": [
          {
            "datasource": {
              "type": "prometheus",
              "uid": "Prometheus"
            },
            "refId": "A"
          }
        ],
        "title": "Bulkhead Metrics",
        "type": "row"
      },
      {
        "datasource": {
          "type": "prometheus",
          "uid": "Prometheus"
        },
        "description": "Percentage of calls which were rejected by a bulkhead over the last $avg_period.",
        "fieldConfig": {
          "defaults": {
            "color": {
              "mode": "palette-classic"
            },
            "custom": {
              "axisLabel": "",
              "axisPlacement": "auto",
              "barAlignment": 0,
              "drawStyle": "line",
              "fillOpacity": 10,
              "gradientMode": "none",
              "hideFrom": {
                "legend": false,
                "tooltip": false,
                "viz": false
              },
              "lineInterpolation": "linear",
              "lineWidth": 1,
              "pointSize": 5,
              "scaleDistribution": {
                "type": "linear"
              },
              "showPoints": "never",
              "spanNulls": false,
              "stacking": {
                "group": "A",
                "mode": "none"
              },
              "thresholdsStyle": {
                "mode": "off"
              }
            },
            "links": [],
            "mappings": [],
            "max": 101,
            "min": 0,
            "thresholds": {
              "mode": "absolute",
              "steps": [
                {
                  "color": "green",
                  "value": null
                },
                {
                  "color": "red",
                  "value": 80
                }
              ]
            },
            "unit": "percent"
          },
          "overrides": []
        },
        "gridPos": {
          "h": 9,
          "w": 12,
          "x": 0,
          "y": 66
        },
        "id": 12,
        "links": [],
        "options": {
          "legend": {
            "calcs": [
              "mean",
              "max",
              "min"
            ],
            "displayMode": "table",
            "placement": "bottom"
          },
          "tooltip": {
            "mode": "multi",
            "sort": "none"
          }
        },
        "pluginVersion": "9.0.2",
        "targets": [
          {
            "datasource": {
              "type": "prometheus",
              "uid": "Prometheus"
            },
            "expr": "sum without (bulkheadResult)(rate(base_ft_bulkhead_calls_total{instance=~`${instance}`, bulkheadResult='rejected'}[$avg_period])*100)\n/\nsum without (bulkheadResult)(rate(base_ft_bulkhead_calls_total{instance=~`${instance}`}[$avg_period]))",
            "format": "time_series",
            "interval": "",
            "intervalFactor": 1,
            "legendFormat": "instance: {{instance}}, method: {{method}}",
            "refId": "A"
          }
        ],
        "title": "Invocations rejected by bulkhead [%, avg $avg_period]",
        "type": "timeseries"
      },
      {
        "datasource": {
          "type": "prometheus",
          "uid": "Prometheus"
        },
        "description": "Estimate of the number of concurrent calls that are attempted through a bulkhead.\n\nThis is done by multiplying the number of attempted invocations by the mean execution time.",
        "fieldConfig": {
          "defaults": {
            "color": {
              "mode": "palette-classic"
            },
            "custom": {
              "axisLabel": "Concurrent attempts",
              "axisPlacement": "auto",
              "barAlignment": 0,
              "drawStyle": "line",
              "fillOpacity": 10,
              "gradientMode": "none",
              "hideFrom": {
                "legend": false,
                "tooltip": false,
                "viz": false
              },
              "lineInterpolation": "linear",
              "lineWidth": 1,
              "pointSize": 5,
              "scaleDistribution": {
                "type": "linear"
              },
              "showPoints": "never",
              "spanNulls": false,
              "stacking": {
                "group": "A",
                "mode": "none"
              },
              "thresholdsStyle": {
                "mode": "off"
              }
            },
            "links": [],
            "mappings": [],
            "min": 0,
            "thresholds": {
              "mode": "absolute",
              "steps": [
                {
                  "color": "green",
                  "value": null
                },
                {
                  "color": "red",
                  "value": 80
                }
              ]
            },
            "unit": "short"
          },
          "overrides": []
        },
        "gridPos": {
          "h": 9,
          "w": 12,
          "x": 12,
          "y": 66
        },
        "id": 20,
        "links": [],
        "options": {
          "legend": {
            "calcs": [
              "mean",
              "lastNotNull",
              "max",
              "min"
            ],
            "displayMode": "table",
            "placement": "bottom"
          },
          "tooltip": {
            "mode": "multi",
            "sort": "none"
          }
        },
        "pluginVersion": "9.0.2",
        "targets": [
          {
            "datasource": {
              "type": "prometheus",
              "uid": "Prometheus"
            },
            "expr": "sum without (bulkheadResult)(rate(base_ft_bulkhead_calls_total{instance=~`${instance}`}[30s]))\n*\nbase_ft_bulkhead_runningDuration_mean_seconds{instance=~`${instance}`}",
            "format": "time_series",
            "interval": "",
            "intervalFactor": 1,
            "legendFormat": "instance: {{instance}}, method: {{method}}",
            "refId": "A"
          }
        ],
        "title": "Estimated number of attempted concurrent calls through a bulkhead [avg 1m]",
        "type": "timeseries"
      },
      {
        "datasource": {
          "type": "prometheus",
          "uid": "Prometheus"
        },
        "description": "The average duration a method with a bulkhead runs for to return a value, using a weighted average of the last 1000 executions.",
        "fieldConfig": {
          "defaults": {
            "color": {
              "mode": "palette-classic"
            },
            "custom": {
              "axisLabel": "",
              "axisPlacement": "auto",
              "barAlignment": 0,
              "drawStyle": "line",
              "fillOpacity": 10,
              "gradientMode": "none",
              "hideFrom": {
                "legend": false,
                "tooltip": false,
                "viz": false
              },
              "lineInterpolation": "linear",
              "lineWidth": 1,
              "pointSize": 5,
              "scaleDistribution": {
                "type": "linear"
              },
              "showPoints": "never",
              "spanNulls": false,
              "stacking": {
                "group": "A",
                "mode": "none"
              },
              "thresholdsStyle": {
                "mode": "off"
              }
            },
            "links": [],
            "mappings": [],
            "thresholds": {
              "mode": "absolute",
              "steps": [
                {
                  "color": "green",
                  "value": null
                },
                {
                  "color": "red",
                  "value": 80
                }
              ]
            },
            "unit": "s"
          },
          "overrides": []
        },
        "gridPos": {
          "h": 9,
          "w": 12,
          "x": 0,
          "y": 75
        },
        "id": 44,
        "options": {
          "legend": {
            "calcs": [
              "max",
              "min"
            ],
            "displayMode": "table",
            "placement": "bottom"
          },
          "tooltip": {
            "mode": "multi",
            "sort": "none"
          }
        },
        "pluginVersion": "9.0.2",
        "targets": [
          {
            "datasource": {
              "type": "prometheus",
              "uid": "Prometheus"
            },
            "expr": "base_ft_bulkhead_runningDuration_mean_seconds{instance=~`${instance}`}",
            "interval": "",
            "legendFormat": "instance: {{instance}}, method: {{method}}",
            "refId": "A"
          }
        ],
        "title": "Mean execution duration for methods with a bulkhead [s, avg 1000 exec.]",
        "type": "timeseries"
      },
      {
        "datasource": {
          "type": "prometheus",
          "uid": "Prometheus"
        },
        "description": "Shows the selected quantile of execution times, for methods running with a bulkhead, using a weighted average of the last 1000 executions.\n\nThe quantiles should be understood like this: if the 0.99 quantile is 300ms, then 99% of executions took less than 300ms. (Conversely, 1% of executions took longer than 300ms.)",
        "fieldConfig": {
          "defaults": {
            "color": {
              "mode": "palette-classic"
            },
            "custom": {
              "axisLabel": "",
              "axisPlacement": "auto",
              "barAlignment": 0,
              "drawStyle": "line",
              "fillOpacity": 10,
              "gradientMode": "none",
              "hideFrom": {
                "legend": false,
                "tooltip": false,
                "viz": false
              },
              "lineInterpolation": "linear",
              "lineWidth": 1,
              "pointSize": 5,
              "scaleDistribution": {
                "type": "linear"
              },
              "showPoints": "never",
              "spanNulls": false,
              "stacking": {
                "group": "A",
                "mode": "none"
              },
              "thresholdsStyle": {
                "mode": "off"
              }
            },
            "links": [],
            "mappings": [],
            "min": 0,
            "thresholds": {
              "mode": "absolute",
              "steps": [
                {
                  "color": "green",
                  "value": null
                },
                {
                  "color": "red",
                  "value": 80
                }
              ]
            },
            "unit": "s"
          },
          "overrides": []
        },
        "gridPos": {
          "h": 9,
          "w": 12,
          "x": 12,
          "y": 75
        },
        "id": 14,
        "links": [],
        "options": {
          "legend": {
            "calcs": [
              "lastNotNull"
            ],
            "displayMode": "table",
            "placement": "bottom"
          },
          "tooltip": {
            "mode": "multi",
            "sort": "none"
          }
        },
        "pluginVersion": "9.0.2",
        "targets": [
          {
            "datasource": {
              "type": "prometheus",
              "uid": "Prometheus"
            },
            "expr": "base_ft_bulkhead_runningDuration_seconds{instance=~`${instance}`, quantile=`${quantile}`}",
            "format": "time_series",
            "instant": false,
            "interval": "",
            "intervalFactor": 1,
            "legendFormat": "instance: {{instance}}, method: {{method}}",
            "refId": "A"
          }
        ],
        "title": "$quantile quantile of execution duration for methods with a bulkhead [s, avg 1000 exec.]",
        "type": "timeseries"
      },
      {
        "collapsed": false,
        "datasource": {
          "type": "prometheus",
          "uid": "Prometheus"
        },
        "gridPos": {
          "h": 1,
          "w": 24,
          "x": 0,
          "y": 84
        },
        "id": 26,
        "panels": [],
        "targets": [
          {
            "datasource": {
              "type": "prometheus",
              "uid": "Prometheus"
            },
            "refId": "A"
          }
        ],
        "title": "Circuit Breaker Metrics",
        "type": "row"
      },
      {
        "datasource": {
          "type": "prometheus",
          "uid": "Prometheus"
        },
        "description": "Percentage of calls which were rejected by an open circuit breaker over the last $avg_period.",
        "fieldConfig": {
          "defaults": {
            "color": {
              "mode": "palette-classic"
            },
            "custom": {
              "axisLabel": "",
              "axisPlacement": "auto",
              "barAlignment": 0,
              "drawStyle": "line",
              "fillOpacity": 10,
              "gradientMode": "none",
              "hideFrom": {
                "legend": false,
                "tooltip": false,
                "viz": false
              },
              "lineInterpolation": "linear",
              "lineWidth": 1,
              "pointSize": 5,
              "scaleDistribution": {
                "type": "linear"
              },
              "showPoints": "never",
              "spanNulls": false,
              "stacking": {
                "group": "A",
                "mode": "none"
              },
              "thresholdsStyle": {
                "mode": "off"
              }
            },
            "links": [],
            "mappings": [],
            "max": 101,
            "min": 0,
            "thresholds": {
              "mode": "absolute",
              "steps": [
                {
                  "color": "green",
                  "value": null
                },
                {
                  "color": "red",
                  "value": 80
                }
              ]
            },
            "unit": "percent"
          },
          "overrides": []
        },
        "gridPos": {
          "h": 9,
          "w": 12,
          "x": 0,
          "y": 85
        },
        "id": 40,
        "options": {
          "legend": {
            "calcs": [
              "mean",
              "max",
              "min"
            ],
            "displayMode": "table",
            "placement": "bottom"
          },
          "tooltip": {
            "mode": "multi",
            "sort": "none"
          }
        },
        "pluginVersion": "9.0.2",
        "targets": [
          {
            "datasource": {
              "type": "prometheus",
              "uid": "Prometheus"
            },
            "expr": "sum without (circuitBreakerResult)(rate(base_ft_circuitbreaker_calls_total{instance=~`${instance}`, circuitBreakerResult='circuitBreakerOpen'}[$avg_period])*100)\n/\nsum without (circuitBreakerResult)(rate(base_ft_circuitbreaker_calls_total{instance=~`${instance}`}[$avg_period]))",
            "interval": "",
            "legendFormat": "instance: {{instance}}, method: {{method}}",
            "refId": "A"
          }
        ],
        "title": "Invocations rejected by an open circuit breaker [%, avg $avg_period]",
        "type": "timeseries"
      },
      {
        "datasource": {
          "type": "prometheus",
          "uid": "Prometheus"
        },
        "description": "Percentage of invocations which were permitted to run by a circuit breaker but failed.",
        "fieldConfig": {
          "defaults": {
            "color": {
              "mode": "palette-classic"
            },
            "custom": {
              "axisLabel": "Failure %",
              "axisPlacement": "auto",
              "barAlignment": 0,
              "drawStyle": "line",
              "fillOpacity": 10,
              "gradientMode": "none",
              "hideFrom": {
                "legend": false,
                "tooltip": false,
                "viz": false
              },
              "lineInterpolation": "linear",
              "lineWidth": 1,
              "pointSize": 5,
              "scaleDistribution": {
                "type": "linear"
              },
              "showPoints": "never",
              "spanNulls": false,
              "stacking": {
                "group": "A",
                "mode": "none"
              },
              "thresholdsStyle": {
                "mode": "off"
              }
            },
            "links": [],
            "mappings": [],
            "max": 101,
            "min": 0,
            "thresholds": {
              "mode": "absolute",
              "steps": [
                {
                  "color": "green",
                  "value": null
                },
                {
                  "color": "red",
                  "value": 80
                }
              ]
            },
            "unit": "percent"
          },
          "overrides": []
        },
        "gridPos": {
          "h": 9,
          "w": 12,
          "x": 12,
          "y": 85
        },
        "id": 18,
        "links": [],
        "options": {
          "legend": {
            "calcs": [
              "mean",
              "max",
              "min"
            ],
            "displayMode": "table",
            "placement": "bottom"
          },
          "tooltip": {
            "mode": "multi",
            "sort": "none"
          }
        },
        "pluginVersion": "9.0.2",
        "repeat": "method",
        "repeatDirection": "v",
        "targets": [
          {
            "datasource": {
              "type": "prometheus",
              "uid": "Prometheus"
            },
            "expr": "sum without (circuitBreakerResult)(rate(base_ft_circuitbreaker_calls_total{instance=~`${instance}`, circuitBreakerResult='failure'}[$avg_period]))*100\n/\nsum without (circuitBreakerResult)(rate(base_ft_circuitbreaker_calls_total{instance=~`${instance}`, circuitBreakerResult=~'success|failure'}[$avg_period]))",
            "format": "time_series",
            "interval": "",
            "intervalFactor": 1,
            "legendFormat": "instance: {{instance}}, method: {{method}}",
            "refId": "A"
          }
        ],
        "title": "Failed calls permitted by circuit breaker [%, avg $avg_period]",
        "type": "timeseries"
      },
      {
        "datasource": {
          "type": "prometheus",
          "uid": "Prometheus"
        },
        "description": "Shows the percentage of time per-second that a circuit breaker spends in an open or half-open state.\n\nThe graph checks back for up to 1 minute for the two most recent data points.",
        "fieldConfig": {
          "defaults": {
            "color": {
              "mode": "palette-classic"
            },
            "custom": {
              "axisLabel": "Percentage of time not closed per second",
              "axisPlacement": "auto",
              "barAlignment": 0,
              "drawStyle": "line",
              "fillOpacity": 10,
              "gradientMode": "none",
              "hideFrom": {
                "legend": false,
                "tooltip": false,
                "viz": false
              },
              "lineInterpolation": "linear",
              "lineWidth": 1,
              "pointSize": 5,
              "scaleDistribution": {
                "type": "linear"
              },
              "showPoints": "never",
              "spanNulls": false,
              "stacking": {
                "group": "A",
                "mode": "none"
              },
              "thresholdsStyle": {
                "mode": "off"
              }
            },
            "links": [],
            "mappings": [],
            "max": 101,
            "min": 0,
            "thresholds": {
              "mode": "absolute",
              "steps": [
                {
                  "color": "green",
                  "value": null
                },
                {
                  "color": "red",
                  "value": 80
                }
              ]
            },
            "unit": "percent"
          },
          "overrides": []
        },
        "gridPos": {
          "h": 9,
          "w": 12,
          "x": 0,
          "y": 94
        },
        "id": 16,
        "links": [],
        "options": {
          "legend": {
            "calcs": [
              "mean",
              "lastNotNull"
            ],
            "displayMode": "table",
            "placement": "bottom"
          },
          "tooltip": {
            "mode": "multi",
            "sort": "none"
          }
        },
        "pluginVersion": "9.0.2",
        "targets": [
          {
            "datasource": {
              "type": "prometheus",
              "uid": "Prometheus"
            },
            "expr": "sum without (state)(irate(base_ft_circuitbreaker_state_total_seconds{instance=~`${instance}`, state!='closed'}[1m])*100)",
            "format": "time_series",
            "interval": "",
            "intervalFactor": 1,
            "legendFormat": "instance: {{instance}}, method: {{method}}",
            "refId": "A"
          }
        ],
        "title": "Circuit breaker open or half-open [%]",
        "type": "timeseries"
      }
    ],
    "refresh": "5s",
    "schemaVersion": 36,
    "style": "dark",
    "tags": [],
    "templating": {
      "list": [
        {
          "current": {},
          "datasource": {
            "type": "prometheus",
            "uid": "Prometheus"
          },
          "definition": "base_ft_invocations_total",
          "hide": 0,
          "includeAll": true,
          "label": "Instance",
          "multi": true,
          "name": "instance",
          "options": [],
          "query": {
            "query": "base_ft_invocations_total",
            "refId": "Prometheus-instance-Variable-Query"
          },
          "refresh": 1,
          "regex": "/base_ft_invocations_total{.*instance=\"(.*?)\",.*/",
          "skipUrlSync": false,
          "sort": 1,
          "tagValuesQuery": "",
          "tagsQuery": "",
          "type": "query",
          "useTags": false
        },
        {
          "current": {
            "selected": true,
            "text": "30s",
            "value": "30s"
          },
          "hide": 0,
          "includeAll": false,
          "label": "Moving Average Period",
          "multi": false,
          "name": "avg_period",
          "options": [
            {
              "selected": true,
              "text": "30s",
              "value": "30s"
            },
            {
              "selected": false,
              "text": "1m",
              "value": "1m"
            },
            {
              "selected": false,
              "text": "3m",
              "value": "3m"
            },
            {
              "selected": false,
              "text": "5m",
              "value": "5m"
            },
            {
              "selected": false,
              "text": "10m",
              "value": "10m"
            }
          ],
          "query": "30s, 1m, 3m, 5m, 10m",
          "queryValue": "",
          "skipUrlSync": false,
          "type": "custom"
        },
        {
          "current": {
            "selected": false,
            "text": "0.5",
            "value": "0.5"
          },
          "hide": 0,
          "includeAll": false,
          "label": "Quantile",
          "multi": false,
          "name": "quantile",
          "options": [
            {
              "selected": true,
              "text": "0.5",
              "value": "0.5"
            },
            {
              "selected": false,
              "text": "0.75",
              "value": "0.75"
            },
            {
              "selected": false,
              "text": "0.95",
              "value": "0.95"
            },
            {
              "selected": false,
              "text": "0.98",
              "value": "0.98"
            },
            {
              "selected": false,
              "text": "0.99",
              "value": "0.99"
            },
            {
              "selected": false,
              "text": "0.999",
              "value": "0.999"
            }
          ],
          "query": "0.5, 0.75, 0.95, 0.98, 0.99, 0.999",
          "queryValue": "",
          "skipUrlSync": false,
          "type": "custom"
        },
        {
          "current": {
            "selected": false,
            "text": "3",
            "value": "3"
          },
          "hide": 0,
          "includeAll": false,
          "label": "Top K Values",
          "multi": false,
          "name": "topK",
          "options": [
            {
              "selected": true,
              "text": "3",
              "value": "3"
            },
            {
              "selected": false,
              "text": "5",
              "value": "5"
            },
            {
              "selected": false,
              "text": "10",
              "value": "10"
            }
          ],
          "query": "3,5,10",
          "skipUrlSync": false,
          "type": "custom"
        }
      ]
    },
    "time": {
      "from": "now-30m",
      "to": "now"
    },
    "timepicker": {
      "refresh_intervals": [
        "10s",
        "30s",
        "1m",
        "5m",
        "15m",
        "30m",
        "1h",
        "2h",
        "1d"
      ],
      "time_options": [
        "5m",
        "15m",
        "1h",
        "6h",
        "12h",
        "24h",
        "2d",
        "7d",
        "30d"
      ]
    },
    "title": "Quarkus Fault Tolerance"
  }
}